Metadata-Version: 2.1
Name: fastode
Version: 0.1.5
Summary: A toolset to help make python coding faster
Home-page: https://github.com/zbc0315/fastode
Author: zhang
Author-email: zhangbc0315@outlook.com
Classifier: Programming Language :: Python :: 3
Classifier: License :: OSI Approved :: MIT License
Classifier: Operating System :: OS Independent
Requires-Python: >=3.5
License-File: LICENSE
